dorado/__init__.py
dorado/lagrangian_walker.py
dorado/parallel_routing.py
dorado/particle_track.py
dorado/routines.py
dorado/spatial.py
dorado/example_data/__init__.py
dorado/example_data/define_params.py
dorado/example_data/ex_anuga_data.npz
dorado/example_data/ex_deltarcm_data.npz
pydorado-2.6.0.dist-info/licenses/LICENSE
pydorado-2.6.0.dist-info/METADATA
pydorado-2.6.0.dist-info/WHEEL
pydorado-2.6.0.dist-info/top_level.txt
pydorado-2.6.0.dist-info/RECORD
