Metadata-Version: 2.4
Name: pydorado
Version: 2.6.0
Summary: dorado - Lagrangian particle routing routine via weighted random walks
Author-email: "J. Hariharan" <jayaram.hariharan@utexas.edu>, "K. Wright" <kyle.wright@twdb.texas.gov>, "P. Passalacqua" <paola@austin.utexas.edu>
Maintainer-email: "J. Hariharan" <jayaram.hariharan@utexas.edu>, "K. Wright" <kyle.wright@twdb.texas.gov>
License: MIT License
Project-URL: Homepage, https://github.com/passaH2O/dorado
Project-URL: Bug Reports, https://github.com/passaH2O/dorado/issues
Project-URL: Source, https://github.com/passaH2O/dorado
Classifier: Programming Language :: Python :: 3.11
Classifier: Programming Language :: Python :: 3.12
Classifier: Programming Language :: Python :: 3.13
Classifier: Programming Language :: Python :: 3.14
Requires-Python: >=2.7
License-File: LICENSE
Requires-Dist: numpy
Requires-Dist: matplotlib
Requires-Dist: scipy
Requires-Dist: future
Requires-Dist: tqdm
Provides-Extra: dev
Requires-Dist: pytest; extra == "dev"
Requires-Dist: pytest-cov; extra == "dev"
Requires-Dist: coveralls; extra == "dev"
Requires-Dist: pydorado[docs]; extra == "dev"
Provides-Extra: docs
Requires-Dist: sphinx; extra == "docs"
Requires-Dist: m2r2; extra == "docs"
Requires-Dist: ipython; extra == "docs"
Requires-Dist: ipykernel; extra == "docs"
Dynamic: license-file
